process_timer/__init__.py
process_timer/process_timer.py
process_timer-1.1.1.dist-info/LICENSE.txt
process_timer-1.1.1.dist-info/METADATA
process_timer-1.1.1.dist-info/WHEEL
process_timer-1.1.1.dist-info/top_level.txt
process_timer-1.1.1.dist-info/RECORD
