Metadata-Version: 2.1
Name: process-timer
Version: 1.1.1
Summary: Celery Timeout decorator
Home-page: https://github.com/sprajosh/process-timer
Author: Siddharth Prajosh
Author-email: sprajosh@gmail.com
License: UNKNOWN
Platform: UNKNOWN
Classifier: Development Status :: 4 - Beta
Classifier: Intended Audience :: Developers
Classifier: License :: OSI Approved :: MIT License
Classifier: Natural Language :: English
Classifier: Operating System :: OS Independent
Classifier: Programming Language :: Python
Classifier: Topic :: Software Development :: Libraries :: Python Modules
Requires-Dist: billiard
